[
  {
    "id": 1,
    "name": "Women's Anorak",
    "style_no": "6WCO1204",
    "description": "Women's hoodie anorak, exposed zip fastening at front, relaxed fit, kangaroo pocket, contrast panels.",
    "material": "woven",
    "constructure": "pk",
    "fabric_no": "FVF05474PNK04",
    "content": "89% Nylon 66, 11% Spandex",
    "image": ["/image/PRODUCT-19.png", "/image/PRODUCT-19-1.jpg", "/image/PRODUCT-19-2.jpg", "/image/PRODUCT-19-3.jpg", "/image/PRODUCT-19-4.jpg", "/image/PRODUCT-19-5.jpg", "/image/PRODUCT-19-6.jpg"],
    "category": "women",
    "style": "jacket",
    "function": ["DWR", "4WAY STRETCH"],
    "colors": "green",
    "size": "S"
  },
  {
    "id": 2,
    "name": "Men's Running Jacket",
    "style_no": "8MRT2023",
    "description": "Lightweight running jacket with water-resistant fabric, breathable mesh lining.",
    "material": "woven",
    "constructure": "ripstop",
    "fabric_no": "FMV03212BLK02",
    "content": "100% Polyester",
    "image": ["/image/PRODUCT-13.png", "/image/PRODUCT-19-1.jpg", "/image/PRODUCT-19-2.jpg", "/image/PRODUCT-19-3.jpg", "/image/PRODUCT-19-4.jpg", "/image/PRODUCT-19-5.jpg", "/image/PRODUCT-19-6.jpg"],
    "category": "men",
    "style": "jacket",
    "function": ["WINDPROOF", "BREATHABLE"],
    "colors": "black",
    "size": "M"
  },
  {
    "id": 3,
    "name": "Women's Yoga Set",
    "style_no": "7WYS5588",
    "description": "Stretchy and comfortable yoga set with seamless design and moisture-wicking fabric.",
    "material": "knit",
    "constructure": "interlock",
    "fabric_no": "FYK07890PURP01",
    "content": "85% Nylon, 15% Spandex",
    "image":  ["/image/PRODUCT-14.png", "/image/PRODUCT-19-1.jpg", "/image/PRODUCT-19-2.jpg", "/image/PRODUCT-19-3.jpg", "/image/PRODUCT-19-4.jpg", "/image/PRODUCT-19-5.jpg", "/image/PRODUCT-19-6.jpg"],
    "category": "women",
    "style": "set",
    "function": ["MOISTURE WICKING", "4WAY STRETCH"],
    "colors": "purple",
    "size": "M"
  },
  {
    "id": 4,
    "name": "Men's Training Shorts",
    "style_no": "9MTS3340",
    "description": "Breathable training shorts with quick-dry technology and elastic waistband.",
    "material": "woven",
    "constructure": "dobby",
    "fabric_no": "FMT09123BLU02",
    "content": "90% Polyester, 10% Spandex",
    "image":  ["/image/PRODUCT-15.png", "/image/PRODUCT-19-1.jpg", "/image/PRODUCT-19-2.jpg", "/image/PRODUCT-19-3.jpg", "/image/PRODUCT-19-4.jpg", "/image/PRODUCT-19-5.jpg", "/image/PRODUCT-19-6.jpg"],
    "category": "men",
    "style": "shorts",
    "function": ["QUICK DRY", "LIGHTWEIGHT"],
    "colors": "blue",
    "size": "L"
  },
  {
    "id": 5,
    "name": "Women's Sports Bra",
    "style_no": "6WSB2205",
    "description": "High support sports bra with adjustable straps and breathable fabric.",
    "material": "knit",
    "constructure": "jersey",
    "fabric_no": "FSB09870RED01",
    "content": "88% Polyester, 12% Elastane",
    "image":  ["/image/PRODUCT-16.png", "/image/PRODUCT-19-1.jpg", "/image/PRODUCT-19-2.jpg", "/image/PRODUCT-19-3.jpg", "/image/PRODUCT-19-4.jpg", "/image/PRODUCT-19-5.jpg", "/image/PRODUCT-19-6.jpg"],
    "category": "women",
    "style": "top",
    "function": ["HIGH SUPPORT", "MOISTURE WICKING"],
    "colors": "red",
    "size": "M"
  },
  {
    "id": 6,
    "name": "Men's Compression Tights",
    "style_no": "8MCT9912",
    "description": "Compression tights for optimal performance and muscle recovery.",
    "material": "knit",
    "constructure": "compression",
    "fabric_no": "FMC06543BLK04",
    "content": "80% Nylon, 20% Spandex",
    "image":  ["/image/PRODUCT-17.png", "/image/PRODUCT-19-1.jpg", "/image/PRODUCT-19-2.jpg", "/image/PRODUCT-19-3.jpg", "/image/PRODUCT-19-4.jpg", "/image/PRODUCT-19-5.jpg", "/image/PRODUCT-19-6.jpg"],
    "category": "men",
    "style": "bottom",
    "function": ["COMPRESSION", "4WAY STRETCH"],
    "colors": "black",
    "size": "L"
  },
  {
    "id": 7,
    "name": "Women's Running Leggings",
    "style_no": "7WRL3045",
    "description": "High-waisted running leggings with side pockets and reflective details.",
    "material": "knit",
    "constructure": "interlock",
    "fabric_no": "FWR04323BLK05",
    "content": "78% Polyester, 22% Elastane",
    "image": ["/image/PRODUCT-18.png", "/image/PRODUCT-19-1.jpg", "/image/PRODUCT-19-2.jpg", "/image/PRODUCT-19-3.jpg", "/image/PRODUCT-19-4.jpg", "/image/PRODUCT-19-5.jpg", "/image/PRODUCT-19-6.jpg"],
    "category": "women",
    "style": "bottom",
    "function": ["REFLECTIVE", "MOISTURE WICKING"],
    "colors": "black",
    "size": "S"
  },
  {
    "id": 8,
    "name": "Men's Training Hoodie",
    "style_no": "9MTH5678",
    "description": "Soft and warm hoodie with adjustable drawstring and front pocket.",
    "material": "knit",
    "constructure": "fleece",
    "fabric_no": "FMH05432GRY03",
    "content": "60% Cotton, 40% Polyester",
    "image": ["/image/PRODUCT-19.png", "/image/PRODUCT-19-1.jpg", "/image/PRODUCT-19-2.jpg", "/image/PRODUCT-19-3.jpg", "/image/PRODUCT-19-4.jpg", "/image/PRODUCT-19-5.jpg", "/image/PRODUCT-19-6.jpg"],
    "category": "men",
    "style": "jacket",
    "function": ["WARM", "SOFT TOUCH"],
    "colors": "gray",
    "size": "XL"
  },
  {
    "id": 9,
    "name": "Women's Tennis Skirt",
    "style_no": "6WTS1280",
    "description": "Flared tennis skirt with built-in shorts for better movement and comfort.",
    "material": "woven",
    "constructure": "taffeta",
    "fabric_no": "FTS00321WHT01",
    "content": "95% Polyester, 5% Spandex",
    "image":  ["/image/PRODUCT-19.png", "/image/PRODUCT-19-1.jpg", "/image/PRODUCT-19-2.jpg", "/image/PRODUCT-19-3.jpg", "/image/PRODUCT-19-4.jpg", "/image/PRODUCT-19-5.jpg", "/image/PRODUCT-19-6.jpg"],
    "category": "women",
    "style": "bottom",
    "function": ["BREATHABLE", "QUICK DRY"],
    "colors": "white",
    "size": "S"
  },
  {
    "id": 10,
    "name": "Men's Puffer Vest",
    "style_no": "8MPV6602",
    "description": "Insulated puffer vest with lightweight padding for extra warmth.",
    "material": "woven",
    "constructure": "quilted",
    "fabric_no": "FPV07891BLU06",
    "content": "100% Nylon",
    "image":  ["/image/PRODUCT-19.png", "/image/PRODUCT-19-1.jpg", "/image/PRODUCT-19-2.jpg", "/image/PRODUCT-19-3.jpg", "/image/PRODUCT-19-4.jpg", "/image/PRODUCT-19-5.jpg", "/image/PRODUCT-19-6.jpg"],
    "category": "men",
    "style": "jacket",
    "function": ["INSULATED", "LIGHTWEIGHT"],
    "colors": "navy blue",
    "size": "L"
  }
]
